LICENSE
README.rst
setup.py
pycoSHARK.egg-info/PKG-INFO
pycoSHARK.egg-info/SOURCES.txt
pycoSHARK.egg-info/dependency_links.txt
pycoSHARK.egg-info/not-zip-safe
pycoSHARK.egg-info/requires.txt
pycoSHARK.egg-info/top_level.txt
pycoshark/__init__.py
pycoshark/mongomodels.py
pycoshark/utils.py