Metadata-Version: 2.1
Name: pycoSHARK
Version: 1.4.4
Summary: Basic MongoDB Models for smartSHARK.
Home-page: https://github.com/smartshark/pycoSHARK
Author: ftrautsch
Author-email: fabian.trautsch@uni-goettingen.de
License: UNKNOWN
Download-URL: https://github.com/smartshark/pycoSHARK/zipball/master
Platform: UNKNOWN
Classifier: Programming Language :: Python :: 3
Classifier: Development Status :: 4 - Beta
Classifier: Environment :: Console
Classifier: Intended Audience :: Developers
Classifier: License :: OSI Approved :: Apache Software License
Classifier: Operating System :: POSIX :: Linux
Classifier: Topic :: Software Development :: Libraries :: Python Modules
License-File: LICENSE
